{
  "game": {
    "id": "439966",
    "ruleset": {
      "name": "standard",
      "version": "v.1.2.3"
    },
    "timeout": 500
  },
  "turn": 200,
  "you": {
    "health": 100,
    "id": "you",
    "name": "#22aa34",
    "body": [
      {
        "x": 0,
        "y": 0
      },
      {
        "x": 1,
        "y": 0
      },
      {
        "x": 1,
        "y": 1
      },
      {
        "x": 0,
        "y": 1
      }
    ],
    "head": {
      "x": 0,
      "y": 0
    },
    "length": 4
  },
  "board": {
    "food": [],
    "hazards": [],
    "height": 11,
    "width": 11,
    "snakes": [
      {
        "health": 100,
        "id": "you",
        "name": "#22aa34",
        "body": [
          {
            "x": 0,
            "y": 0
          },
          {
            "x": 1,
            "y": 0
          },
          {
            "x": 1,
            "y": 1
          },
          {
            "x": 0,
            "y": 1
          }
        ],
        "head": {
          "x": 0,
          "y": 0
        },
        "length": 4
      }
    ]
  }
}
